<doctrine-mapping xmlns="https://doctrine-project.org/schemas/orm/doctrine-mapping"
                  xmlns:xsi="https://www.w3.org/2001/XMLSchema-instance"
                  xsi:schemaLocation="https://doctrine-project.org/schemas/orm/doctrine-mapping
                          https://www.doctrine-project.org/schemas/orm/doctrine-mapping.xsd">
    <entity name="ChameleonSystem\ShopBundle\Entity\ShopCore\shopWrapping" table="shop_wrapping">
        <id name="id" type="string" length="36" column="id" unique="true" />
        <field name="cmsident" type="integer" column="cmsident" unique="true">
            <generator strategy="AUTO"/>
            <options>
                <option name="unsigned">true</option>
            </options>
        </field>
            <field name="Name" type="string" column="name" length="255" nullable="false" >
    <options>
        <option name="comment">Name</option>
        <option name="default"></option>    </options>
</field>
            <field name="Position" type="integer" column="position" nullable="false" >
    <options>
        <option name="comment">Position</option>
        <option name="default"></option>    </options>
</field>
            <many-to-one field="ShopArticle" target-entity="\ChameleonSystem\ShopBundle\Entity\Product\shopArticle">
    <join-column name="shop_article_id" referenced-column-name="id" />
    <options>
        <option name="comment">Wrapping item</option>
    </options>
</many-to-one>
                <lifecycle-callbacks>
                                                                                                        </lifecycle-callbacks>
        
    </entity>

</doctrine-mapping>